{
    "companyName": "MeWoof",
    "userName": "frong",
    "scanId": "23rfer",
    "url": "https",
    "startTime": "--:--:--",
    "stopTime": "--:--:--",
    "duration": "--:--:--",
    "riskScore": 100,
    "risk": [
        {
            "level": 0
        },
        {
            "level": 1
        },
        {
            "level": 2
        },
        {
            "level": 3
        },
        {
            "level": 4
        }
    ],
    "safeCheck": [
        {
            "choice": "safe"
        },
        {
            "choice": "not safe"
        }
    ]
}